README.md
setup.py
expyhist_crawler/__init__.py
expyhist_crawler/aes_encrypt.py
expyhist_crawler/aliyun_email.py
expyhist_crawler/decorator.py
expyhist_crawler/main.py
expyhist_crawler/setting.py
expyhist_crawler.egg-info/PKG-INFO
expyhist_crawler.egg-info/SOURCES.txt
expyhist_crawler.egg-info/dependency_links.txt
expyhist_crawler.egg-info/requires.txt
expyhist_crawler.egg-info/top_level.txt
expyhist_crawler/aop/__init__.py
expyhist_crawler/aop/api/__init__.py
expyhist_crawler/aop/api/base.py
expyhist_crawler/aop/api/biz/UmengApptrackBackReportDataRequest.py
expyhist_crawler/aop/api/biz/UmengApptrackGetActiveDetailDataRequest.py
expyhist_crawler/aop/api/biz/UmengApptrackGetClickActiveDataRequest.py
expyhist_crawler/aop/api/biz/UmengApptrackGetMonitoringListRequest.py
expyhist_crawler/aop/api/biz/UmengApptrackGetMyEventDataRequest.py
expyhist_crawler/aop/api/biz/UmengApptrackGetOrderAnalysisDataRequest.py
expyhist_crawler/aop/api/biz/UmengApptrackGetPayAnalysisDataRequest.py
expyhist_crawler/aop/api/biz/UmengApptrackGetPlanListRequest.py
expyhist_crawler/aop/api/biz/UmengApptrackGetRegisterAnalysisDataRequest.py
expyhist_crawler/aop/api/biz/UmengApptrackGetRegisterLoginDataRequest.py
expyhist_crawler/aop/api/biz/UmengApptrackGetStayTrendDataRequest.py
expyhist_crawler/aop/api/biz/UmengUappCreateAppRequest.py
expyhist_crawler/aop/api/biz/UmengUappEventCreateRequest.py
expyhist_crawler/aop/api/biz/UmengUappEventGetDataRequest.py
expyhist_crawler/aop/api/biz/UmengUappEventGetUniqueUsersRequest.py
expyhist_crawler/aop/api/biz/UmengUappEventListRequest.py
expyhist_crawler/aop/api/biz/UmengUappEventParamGetDataRequest.py
expyhist_crawler/aop/api/biz/UmengUappEventParamGetValueDurationListRequest.py
expyhist_crawler/aop/api/biz/UmengUappEventParamGetValueListRequest.py
expyhist_crawler/aop/api/biz/UmengUappEventParamListRequest.py
expyhist_crawler/aop/api/biz/UmengUappGetActiveAccountsRequest.py
expyhist_crawler/aop/api/biz/UmengUappGetActiveUsersByChannelOrVersionRequest.py
expyhist_crawler/aop/api/biz/UmengUappGetActiveUsersRequest.py
expyhist_crawler/aop/api/biz/UmengUappGetAllAppDataRequest.py
expyhist_crawler/aop/api/biz/UmengUappGetAppCountRequest.py
