Metadata-Version: 1.1
Name: expyhist-crawler
Version: 0.0.6
Summary: simply web crawler
Home-page: https://github.com/expyhist/expyhist_crawler
Author: Expyh
Author-email: exceptionalyh@gmail.com
License: MIT
Platform: UNKNOWN
Classifier: Programming Language :: Python :: 3
Classifier: License :: OSI Approved :: MIT License
Classifier: Operating System :: OS Independent
